new_sched.v
`include "gpu_def.v"

`define SCHED_FENCE (data_frames[global_tp] & 16'b0000000011000000) >> 6

`define WAITING (((data_frames[global_tp + 1] & exec_mask) != 16'h0) || wait_it || \
                ((data_frames[global_tp    ] & `SCHED_FENCE_MASK) >> 6 == `SCHED_FENCE_REL  && exec_mask)) 

//TODO     send r0 data + core and r0 mask
module new_sched
#(
    parameter  DATA_DEPTH = 1024,
    parameter  INSTR_SIZE =   16,
    parameter  FRAME_SIZE =   16,
    parameter    CORE_NUM =   16,
    parameter BUS_TO_CORE =   32,
    parameter    R0_DEPTH =    8
)
// Resolution and refresh rate  
    
    //reploace all the magic numbers by parameters
(
    input  wire clk,
    input  wire reset,
    input  wire core_reading,
    input  wire prog_loading,
    output wire frame_being_sent,
    input  wire [DATA_DEPTH  - 1: 0][INSTR_SIZE - 1: 0] data_frames_in,
    input  wire [CORE_NUM    - 1: 0]                        core_ready,  // may be better reverse it
    
    output  reg [CORE_NUM    - 1: 0]                      init_r0_vect,     // only new  data, old not considered here
    output  reg [BUS_TO_CORE - 1: 0]                      mess_to_core,//

    output  reg [15: 0]        tmp_mess_to_core,
    output  reg [ 7: 0][15: 0]          r0_data
//change for wires where possible
);

    reg [INSTR_SIZE - 1: 0] data_frames [DATA_DEPTH - 1: 0];   // better change type of memory later

    reg [CORE_NUM   - 1: 0]                      exec_mask;//
    reg [CORE_NUM   - 1: 0]                      last_mask;  // cores used by the latest task//
    wire [CORE_NUM   - 1: 0]                    exec_mask2;

    reg [ 5: 0]    if_num;//
    reg [ 9: 0] global_tp;   // [3:0] = tp, [9:4] = frame //
    reg [ 1: 0]     fence;   // barrier . will be deleted. Now needed only for easy testing
    reg           wait_it;//

    integer i; // chacnge for a smaller reg???
    integer k;
    integer j;


    assign exec_mask2 = ~core_ready;


    

/// fence/init_r0_vect/last_mask   reg  logic
    always @(posedge clk) begin
        if (reset) begin
           last_mask <= 0;
           fence     <= 0;
        end 

        else if (!prog_loading && if_num == 0 &&  !(`WAITING)) begin
            fence        <= (data_frames[global_tp    ] & `SCHED_FENCE_MASK) >> 6;
            init_r0_vect <=  data_frames[global_tp + 2];
            last_mask    <=  data_frames[global_tp + 1];
        end
    end



/// mess_to_core + global_tp   reg  logic
    always @(posedge clk) begin
        if (!prog_loading && core_reading && if_num != 0) begin

            /*
            mess_to_core[15:  0] <= data_frames[global_tp    ];
            mess_to_core[31: 16] <= data_frames[global_tp + 1]; //delete it, just change gp
            global_tp <= global_tp + 2; 
            */ // return later, temporally changed
            
            tmp_mess_to_core[15: 0] <= data_frames[global_tp];
        end


    end


/// global_tp  reg  logic
    always @(posedge clk) begin
        if (reset)
           global_tp <= 0;
        
        else if ((!prog_loading) && (if_num == 0) && !(`WAITING)) 
            global_tp <= global_tp + 10'h10;  //step over CF

        else if (!prog_loading && core_reading && if_num != 0)
            global_tp <= global_tp + `SCHED_MSG_BUS_WIDTH; // step over 1 msg
    end


/// if_num  reg  logic
    always @(posedge clk) begin
        if (reset) begin
           if_num <= 0;

        end else if (!prog_loading && if_num && 
                      core_reading && global_tp[3: 0] == 4'b1111) begin  // must be 0000, but not enough time then
            if_num <= if_num - 1;

        end else if (!prog_loading && if_num == 0 && !(`WAITING)) begin
            if_num <= data_frames[global_tp] & `SCHED_IFNUM_MASK; 
        end
    end


    /// exec_mask   reg  logic
    always @(posedge clk) begin
        if (reset)        
           exec_mask <= 0;
                    
        else if (!prog_loading) begin
            exec_mask <= (~core_ready) & exec_mask; // will be deleted
            if (if_num == 0 && !(`WAITING))            
                exec_mask <= exec_mask | data_frames[global_tp + 1]; // to be deleted 
        end
    end  /// may be easily changed for exec_mask2  


    /// last_mask   reg  logic
    always @(posedge clk) begin
        if (reset)        
           last_mask <= 0;
                    
        else if (!prog_loading && if_num == 0 &&  !(`WAITING))
            last_mask <= data_frames[global_tp + 1];
    end


    /// wait_it   reg  logic
    always @(posedge clk) begin
        if (reset)        
           wait_it <= 0;
                    
        else if (!prog_loading && if_num == 0 && !(`WAITING) &&
            (data_frames[global_tp] & `SCHED_FENCE_MASK) >> 6 == `SCHED_FENCE_ACQ)
            wait_it <= 1;

        else if (!(last_mask & exec_mask))
            wait_it <= 0;
    end


    /// data_frames   reg  logic
    always @(posedge clk) begin
        if (prog_loading) begin
            for (j = 0; j < DATA_DEPTH; j++) begin
                data_frames[j] <= data_frames_in[j];
            end
        end
    end


    endmodule

testbench.v
`timescale 1ns/100ps

module testbench;
    parameter  DATA_DEPTH = 1024;

    reg clk;
    reg reset;
    reg core_reading;
    reg [DATA_DEPTH - 1: 0][15: 0] data_frames_in;
    reg [15: 0]              core_ready;
    reg                    prog_loading;
    wire               frame_being_sent;
    integer i; 
    

    always 
        #1 clk = ~clk;


    new_sched #(.DATA_DEPTH(1024), .INSTR_SIZE(16),  .FRAME_SIZE(16), 
                .CORE_NUM(16),     .BUS_TO_CORE(32), .R0_DEPTH(8))    new_sched
                        (
                         .clk             (             clk),
                         .reset           (           reset),
                         .core_ready      (      core_ready),
                         .core_reading    (    core_reading),
                         .prog_loading    (    prog_loading),
                         .data_frames_in  (  data_frames_in),
                         .frame_being_sent(frame_being_sent)

    );
    

    initial begin
        clk          <= 0;
        reset        <= 1;
        core_ready   <= 16'hffff;
        core_reading <= 1;
        prog_loading <= 1;

    end

	initial begin 
		$dumpfile("dump.vcd"); $dumpvars(0, testbench);
        #10;
        reset = 0;
        #10;
        data_frames_in[0]  =  16'h0043;  // new task must not start
        data_frames_in[1]  =  16'h000f;
        data_frames_in[2]  =  16'h000f;

        for (i = 3; i < 64; i = i + 1) begin
            data_frames_in[i] = $random;
        end

        

        data_frames_in[64]  =  16'h0003;
        data_frames_in[65]  =  16'h00f0; // must wait previous. add changin ready flag
        data_frames_in[66]  =  16'h00f0;

        for (i = 67; i < 128; i = i + 1) begin
            data_frames_in[i] = $random;
        end



        data_frames_in[128]  =  16'h0007;
        data_frames_in[129]  =  16'h00f0;
        data_frames_in[130]  =  16'h00f0;

        for (i = 131; i < 256; i = i + 1) begin
            data_frames_in[i] = $random;
        end

        data_frames_in[256]  =  16'h008f;
        data_frames_in[257]  =  16'h0f00;
        data_frames_in[258]  =  16'h0f00;

        for (i = 259; i < 1024; i = i + 1) begin
            data_frames_in[i] = $random;
        end



        #10;
        prog_loading = 0;
        core_ready   = 16'hfff0;

        #35;

        #65;
        core_ready = 16'hff00;

        #60; // 190
        core_ready = 16'hff0f;

        #450;
        core_ready = 16'hffff;

        #2;
        core_ready = 16'hff0f;

        #240;
        core_ready = 16'hffff;
        #2;
        core_ready = 16'hff0f;

/*

/*
        data_frames_in[66: 64]  =  48'h000f000f0003;
        data_frames_in[79: 67] = 208'h1373155187753233769575848246214661179909884209798945;  // 1 frame readay
        //now 3 if: 48 instrs
        data_frames_in[127: 80] = 768'h909349783518983001342480463695987813001572382692929389525816505418711888217498902051905706357098961069882743753078170660315226012310218614980287216204456170791124167120519739573313858667656760
        

        data_frames_in[130: 128]  =  48'hf000f0000003;
        data_frames_in[143: 131] = 208'h1373155187753233769575848246214661179909884209798945;  // 1 frame readay
        //now 3 if: 48 instrs1
        data_frames_in[191: 144] = 768'h909349783518983001342480463695987813001572382692929389525816505418711888217498902051905706357098961069882743753078170660315226012310218614980287216204456170791124167120519739573313858667656760
*/
//        data_frames_in[DATA_DEPTH - 1: 192] = 0;
        #190;
        #450;
        #450;
        $finish;
	end

    




endmodule

build/dump.vcd
$date
	Wed Aug  7 17:18:33 2024
$end
$version
	Icarus Verilog
$end
$timescale
	100ps
$end
$scope module testbench $end
$var wire 1 ! frame_being_sent $end
$var reg 1 " clk $end
$var reg 1 # core_reading $end
$var reg 16 $ core_ready [15:0] $end
$var reg 16384 % data_frames_in [16383:0] $end
$var reg 1 & prog_loading $end
$var reg 1 ' reset $end
$var integer 32 ( i [31:0] $end
$scope module new_sched $end
$var wire 1 " clk $end
$var wire 1 # core_reading $end
$var wire 16 ) core_ready [15:0] $end
$var wire 16384 * data_frames_in [16383:0] $end
$var wire 16 + exec_mask2 [15:0] $end
$var wire 1 ! frame_being_sent $end
$var wire 1 & prog_loading $end
$var wire 1 ' reset $end
$var reg 16 , exec_mask [15:0] $end
$var reg 2 - fence [1:0] $end
$var reg 10 . global_tp [9:0] $end
$var reg 6 / if_num [5:0] $end
$var reg 16 0 init_r0_vect [15:0] $end
$var reg 16 1 last_mask [15:0] $end
$var reg 32 2 mess_to_core [31:0] $end
$var reg 128 3 r0_data [127:0] $end
$var reg 16 4 tmp_mess_to_core [15:0] $end
$var reg 1 5 wait_it $end
$var integer 32 6 j [31:0] $end
$upscope $end
$upscope $end
$enddefinitions $end
#0
$dumpvars
bx 6
x5
bx 4
bx 3
bx 2
bx 1
bx 0
bx /
bx .
bx -
bx ,
b0 +
bx *
b1111111111111111 )
bx (
1'
1&
bx %
b1111111111111111 $
1#
0"
z!
$end
#10
b0 -
b0 .
b0 /
b0 ,
b0 1
05
b10000000000 6
1"
#20
0"
#30
b10000000000 6
1"
#40
0"
#50
b10000000000 6
1"
#60
0"
#70
b10000000000 6
1"
#80
0"
#90
b10000000000 6
1"
#100
0"
0'
#110
b10000000000 6
1"
#120
0"
#130
b10000000000 6
1"
#140
0"
#150
b10000000000 6
1"
#160
0"
#170
b10000000000 6
1"
#180
0"
#190
b10000000000 6
1"
